LICENSE
MANIFEST.in
README.md
dependencies.txt
pyproject.toml
setup.py
map2loop/__init__.py
map2loop/aus_state_urls.py
map2loop/config.py
map2loop/contact_extractor.py
map2loop/data_checks.py
map2loop/deformation_history.py
map2loop/fault_orientation.py
map2loop/interpolators.py
map2loop/logging.py
map2loop/m2l_enums.py
map2loop/mapdata.py
map2loop/project.py
map2loop/sampler.py
map2loop/sorter.py
map2loop/stratigraphic_column.py
map2loop/thickness_calculator.py
map2loop/throw_calculator.py
map2loop/topology.py
map2loop/version.py
map2loop.egg-info/PKG-INFO
map2loop.egg-info/SOURCES.txt
map2loop.egg-info/dependency_links.txt
map2loop.egg-info/requires.txt
map2loop.egg-info/top_level.txt
map2loop/_datasets/clut_files/QLD_clut.csv
map2loop/_datasets/clut_files/SA_clut.csv
map2loop/_datasets/clut_files/WA_clut.csv
map2loop/_datasets/config_files/NSW.json
map2loop/_datasets/config_files/QLD.json
map2loop/_datasets/config_files/SA.json
map2loop/_datasets/config_files/TAS.json
map2loop/_datasets/config_files/VIC.json
map2loop/_datasets/config_files/WA.json
map2loop/_datasets/geodata_files/load_map2loop_data.py
map2loop/_datasets/geodata_files/hamersley/dtm_rp.tif
map2loop/_datasets/geodata_files/hamersley/faults.geojson
map2loop/_datasets/geodata_files/hamersley/geology.geojson
map2loop/_datasets/geodata_files/hamersley/structures.geojson
map2loop/utils/__init__.py
map2loop/utils/load_map2loop_data.py
map2loop/utils/utility_functions.py
tests/test_import.py