Metadata-Version: 2.4
Name: map2loop
Version: 3.2.10
Summary: Generate 3D model data from 2D maps.
Author: Loop team
License: MIT
Project-URL: Documentation, https://Loop3d.org/map2loop/
Project-URL: Bug Tracker, https://github.com/Loop3D/map2loop/issues
Project-URL: Source Code, https://github.com/Loop3D/map2loop
Keywords: earth sciences,geology,3-D modelling,structural geology,uncertainty
Classifier: Development Status :: 4 - Beta
Classifier: Intended Audience :: Science/Research
Classifier: Natural Language :: English
Classifier: Programming Language :: Python
Classifier: Programming Language :: Python :: 3
Classifier: License :: OSI Approved :: MIT License
Classifier: Operating System :: OS Independent
Classifier: Topic :: Scientific/Engineering
Classifier: Topic :: Scientific/Engineering :: GIS
Requires-Python: >=3.8
License-File: LICENSE
Requires-Dist: numpy
Requires-Dist: scipy
Requires-Dist: geopandas
Requires-Dist: shapely>=2
Requires-Dist: networkx
Requires-Dist: owslib
Requires-Dist: loopprojectfile==0.2.2
Requires-Dist: beartype
Requires-Dist: pytest
Requires-Dist: scikit-learn
Dynamic: license-file
